zdppy_api/__init__.py
zdppy_api/anyio/__init__.py
zdppy_api/anyio/_backends/__init__.py
zdppy_api/anyio/_backends/_asyncio.py
zdppy_api/anyio/_backends/_trio.py
zdppy_api/anyio/_core/__init__.py
zdppy_api/anyio/_core/_compat.py
zdppy_api/anyio/_core/_eventloop.py
zdppy_api/anyio/_core/_exceptions.py
zdppy_api/anyio/_core/_fileio.py
zdppy_api/anyio/_core/_resources.py
zdppy_api/anyio/_core/_signals.py
zdppy_api/anyio/_core/_sockets.py
zdppy_api/anyio/_core/_streams.py
zdppy_api/anyio/_core/_subprocesses.py
zdppy_api/anyio/_core/_synchronization.py
zdppy_api/anyio/_core/_tasks.py
zdppy_api/anyio/_core/_testing.py
zdppy_api/anyio/_core/_typedattr.py
zdppy_api/anyio/abc/__init__.py
zdppy_api/anyio/abc/_resources.py
zdppy_api/anyio/abc/_sockets.py
zdppy_api/anyio/abc/_streams.py
zdppy_api/anyio/abc/_subprocesses.py
zdppy_api/anyio/abc/_tasks.py
zdppy_api/anyio/abc/_testing.py
zdppy_api/anyio/from_thread.py
zdppy_api/anyio/lowlevel.py
zdppy_api/anyio/py.typed
zdppy_api/anyio/streams/__init__.py
zdppy_api/anyio/streams/buffered.py
zdppy_api/anyio/streams/file.py
zdppy_api/anyio/streams/memory.py
zdppy_api/anyio/streams/stapled.py
zdppy_api/anyio/streams/text.py
zdppy_api/anyio/streams/tls.py
zdppy_api/anyio/to_process.py
zdppy_api/anyio/to_thread.py
zdppy_api/applications.py
zdppy_api/background.py
zdppy_api/concurrency.py
zdppy_api/datastructures.py
zdppy_api/dependencies/__init__.py
zdppy_api/dependencies/models.py
zdppy_api/dependencies/utils.py
zdppy_api/encoders.py
zdppy_api/exception_handlers.py
zdppy_api/exceptions.py
zdppy_api/logger.py
zdppy_api/middleware/__init__.py
zdppy_api/middleware/asyncexitstack.py
zdppy_api/middleware/cors.py
zdppy_api/middleware/gzip.py
zdppy_api/middleware/httpsredirect.py
zdppy_api/middleware/trustedhost.py
zdppy_api/middleware/wsgi.py
zdppy_api/middlewares.py
zdppy_api/multipart/__init__.py
zdppy_api/multipart/_version.py
zdppy_api/multipart/decoders.py
zdppy_api/multipart/exceptions.py
zdppy_api/multipart/multipart.py
zdppy_api-0.1.1.dist-info/WHEEL
zdppy_api-0.1.1.dist-info/METADATA
zdppy_api-0.1.1.dist-info/RECORD
