Metadata-Version: 2.1
Name: zdppy-api
Version: 0.1.1
Summary: 
Author: zhangdapeng520
Author-email: pygosuperman@outlook.com
Requires-Python: >=3.10,<4.0
Classifier: Programming Language :: Python :: 3
Classifier: Programming Language :: Python :: 3.10
Requires-Dist: anyio (>=3.6.1,<4.0.0)
Requires-Dist: pydantic (>=1.9.1,<2.0.0)
Requires-Dist: python-multipart (>=0.0.5,<0.0.6)
Requires-Dist: uvicorn (>=0.17.6,<0.18.0)
